sanic_oauth/__init__.py
sanic_oauth/blueprint.py
sanic_oauth/core.py
sanic_oauth/providers.py
tests/__init__.py
tests/base_test.py
sanic_oauth-0.4.0.dist-info/LICENSE.txt
sanic_oauth-0.4.0.dist-info/METADATA
sanic_oauth-0.4.0.dist-info/WHEEL
sanic_oauth-0.4.0.dist-info/top_level.txt
sanic_oauth-0.4.0.dist-info/RECORD
