Metadata-Version: 2.1
Name: sanic-oauth
Version: 0.4.0
Summary: UNKNOWN
Home-page: https://gitlab.com/SirEdvin/sanic-oauth
Author: Gladyshev Bogdan
Author-email: siredvin.dark@gmail.com
License: MIT
Keywords: asyncio,http,oauth,sanic
Platform: UNKNOWN
Classifier: Development Status :: 5 - Production/Stable
Classifier: Intended Audience :: Developers
Classifier: License :: OSI Approved :: MIT License
Classifier: Natural Language :: English
Classifier: Natural Language :: Russian
Classifier: Operating System :: OS Independent
Classifier: Programming Language :: Python :: 3
Classifier: Programming Language :: Python
Classifier: Framework :: AsyncIO
Classifier: Topic :: Software Development :: Libraries :: Python Modules
Classifier: Topic :: Software Development :: Testing
Classifier: Topic :: Utilities
Requires-Dist: yarl (~=1.2.6)
Requires-Dist: aiohttp (~=3.3.2)
